chat2func/__init__.py
chat2func/api.py
chat2func/deploy.py
chat2func/functions.py
chat2func/schema.py
chat2func/server.py
chat2func/utils.py
chat2func-0.1.6.dist-info/LICENSE.txt
chat2func-0.1.6.dist-info/METADATA
chat2func-0.1.6.dist-info/WHEEL
chat2func-0.1.6.dist-info/top_level.txt
chat2func-0.1.6.dist-info/RECORD
