Metadata-Version: 2.1
Name: chat2func
Version: 0.1.6
Summary: Automatically creating functions that LLMs can use.
Home-page: https://github.com/ttumiel/chat2func
Author: Thomas Tumiel
License: MIT
Requires-Python: >=3.8
License-File: LICENSE.txt
Requires-Dist: docstring-parser
Requires-Dist: pydantic
Requires-Dist: jsonschema
Provides-Extra: develop
Requires-Dist: Flask ; extra == 'develop'
Requires-Dist: Flask-Cors ; extra == 'develop'
Requires-Dist: PyYAML ; extra == 'develop'
Requires-Dist: openai ; extra == 'develop'
Requires-Dist: tenacity ; extra == 'develop'
Provides-Extra: test
Requires-Dist: pytest ; extra == 'test'
Requires-Dist: black ; extra == 'test'
Requires-Dist: isort ; extra == 'test'
Requires-Dist: pytest-cov ; extra == 'test'
